{
  "version" : "2",
  "id" : "7552b557-98c8-4510-b66a-91a4b7c99c55",
  "experiment" : {
    "base" : {
      "analysis" : {
        "variableFilters" : [ ],
        "selectedType" : "dynamic",
        "choices" : [ {
          "type" : "dynamic",
          "parameters" : {
            "final_time" : 8,
            "start_time" : 0
          },
          "simulationOptions" : {
            "dynamic_diagnostics" : false,
            "ncp" : 500
          },
          "solverOptions" : {
            "store_event_points" : true
          },
          "compilerOptions" : {
            "c_compiler" : "gcc",
            "generate_html_diagnostics" : false,
            "include_protected_variables" : false
          },
          "runtimeOptions" : { }
        } ],
        "expansion" : {
          "discreteAlgorithm" : {
            "noOfSamples" : 0,
            "seed" : 0
          },
          "continuousAlgorithm" : {
            "type" : "SOBOL",
            "noOfSamples" : 10,
            "seed" : 0
          }
        }
      },
      "modifiers" : {
        "initializeFrom" : "",
        "variables" : [ ]
      }
    }
  },
  "metadata" : {
    "created" : "2025-02-18 18:02:10.662310291",
    "lastModified" : "2025-02-18 18:02:10.662310291",
    "name" : "Experiment 1"
  }
}